edgefarm_application/__init__.py
edgefarm_application/version.py
edgefarm_application/ads_node_module/__init__.py
edgefarm_application/ads_node_module/ads_data.avsc
edgefarm_application/ads_node_module/encoder.py
edgefarm_application/ads_node_module/producer.py
edgefarm_application/alm_mqtt_module/__init__.py
edgefarm_application/alm_mqtt_module/client.py
edgefarm_application/alm_mqtt_module/pubRequest.avsc
edgefarm_application/alm_mqtt_module/registerSubRequest.avsc
edgefarm_application/alm_mqtt_module/reqResRequest.avsc
edgefarm_application/alm_mqtt_module/unregisterSubRequest.avsc
edgefarm_application/base/__init__.py
edgefarm_application/base/application_module.py
edgefarm_application/base/avro.py
edgefarm_application/base/iotedge_twin.py
edgefarm_application/base/network.py
edgefarm_application/base/schema.py
edgefarm_application-0.2.2.dist-info/LICENSE
edgefarm_application-0.2.2.dist-info/METADATA
edgefarm_application-0.2.2.dist-info/WHEEL
edgefarm_application-0.2.2.dist-info/top_level.txt
edgefarm_application-0.2.2.dist-info/RECORD
