Metadata-Version: 2.1
Name: edgefarm-application
Version: 0.2.2
Summary: A python library for EdgeFarm applications
Home-page: https://github.com/edgefarm/edgefarm-application-sdk.py
Author: Ci4Rail GmbH
Author-email: engineering@ci4rail.com
License: UNKNOWN
Project-URL: Source Code, https://github.com/edgefarm/edgefarm-application-sdk.py.git
Platform: UNKNOWN
Classifier: Programming Language :: Python :: 3
Classifier: Operating System :: OS Independent
Requires-Dist: asyncio-nats-client (~=0.11.4)
Requires-Dist: fastavro (~=1.4.0)
Requires-Dist: azure-iot-device (~=2.7.0)
